namelist/__init__.py
namelist/namelist.py
namelist-0.1.0.dist-info/LICENSE
namelist-0.1.0.dist-info/METADATA
namelist-0.1.0.dist-info/WHEEL
namelist-0.1.0.dist-info/top_level.txt
namelist-0.1.0.dist-info/RECORD
