Metadata-Version: 2.1
Name: namelist
Version: 0.1.0
Summary: Parsing Fortran namelists to Python dictionaries and back.
Home-page: https://git.geomar.de/martin-claus/py-namelist
Author: Martin Claus
Author-email: mclaus@geomar.de
License: UNKNOWN
Platform: UNKNOWN
Classifier: Programming Language :: Python :: 3
Classifier: License :: OSI Approved :: GNU General Public License v2 (GPLv2)
Classifier: Operating System :: OS Independent
Classifier: Development Status :: 4 - Beta
